{"root":1,"nodes":{"1":{"S1lm":{"$ref":2},"808614":53,"-63713":{"$ref":3},"f7VW":0,"yNAmpf":0,"S1U":{"$ref":4}},"2":{"0":{"$ref":5}},"3":{"1":{"$ref":6},"2":{"$ref":7},"3":{"$ref":8},"4":{"$ref":9},"5":{"$ref":10},"6":{"$ref":11},"7":{"$ref":12},"8":{"$ref":13},"9":{"$ref":14},"10":{"$ref":15},"11":{"$ref":16},"12":{"$ref":17},"13":{"$ref":18},"14":{"$ref":19},"15":{"$ref":20},"16":{"$ref":21},"17":{"$ref":22},"18":{"$ref":23},"19":{"$ref":24},"20":{"$ref":25},"21":{"$ref":26},"22":{"$ref":27},"23":{"$ref":28},"24":{"$ref":29},"25":{"$ref":30},"26":{"$ref":31},"27":{"$ref":32},"28":{"$ref":33},"29":{"$ref":34},"30":{"$ref":35},"31":{"$ref":36},"32":{"$ref":37},"33":{"$ref":38},"34":{"$ref":39},"35":{"$ref":40},"36":{"$ref":41},"37":{"$ref":42},"38":{"$ref":43},"39":{"$ref":44},"40":{"$ref":45},"41":{"$ref":46},"42":{"$ref":47},"43":{"$ref":48},"44":{"$ref":49},"45":{"$ref":50},"46":{"$ref":51},"47":{"$ref":52},"48":{"$ref":53},"49":{"$ref":54},"50":{"$ref":55},"51":{"$ref":56},"52":{"$ref":57},"53":{"$ref":58},"54":{"$ref":59},"55":{"$ref":60},"56":{"$ref":61},"57":{"$ref":62},"58":{"$ref":63},"59":{"$ref":64},"60":{"$ref":65},"61":{"$ref":66},"62":{"$ref":67},"63":{"$ref":68},"64":{"$ref":69},"65":{"$ref":70},"66":{"$ref":71},"67":{"$ref":72},"68":{"$ref":73},"69":{"$ref":74},"70":{"$ref":75},"71":{"$ref":76},"72":{"$ref":77},"73":{"$ref":78},"74":{"$ref":79},"75":{"$ref":80},"76":{"$ref":81},"77":{"$ref":82},"78":{"$ref":83},"79":{"$ref":84},"80":{"$ref":85},"81":{"$ref":86},"82":{"$ref":87},"83":{"$ref":88},"84":{"$ref":89},"85":{"$ref":90},"86":{"$ref":91},"87":{"$ref":92},"88":{"$ref":93},"89":{"$ref":94},"90":{"$ref":95},"91":{"$ref":96},"92":{"$ref":97},"93":{"$ref":98},"94":{"$ref":99},"95":{"$ref":100},"96":{"$ref":101},"97":{"$ref":102},"98":{"$ref":103},"99":{"$ref":104},"100":{"$ref":105},"101":{"$ref":106},"102":{"$ref":107},"103":{"$ref":108},"104":{"$ref":109},"105":{"$ref":110},"106":{"$ref":111},"107":{"$ref":112},"108":{"$ref":113},"109":{"$ref":114},"110":{"$ref":115},"111":{"$ref":116},"112":{"$ref":117},"113":{"$ref":118},"114":{"$ref":119},"115":{"$ref":120},"116":{"$ref":121},"117":{"$ref":122},"118":{"$ref":123},"119":{"$ref":124},"120":{"$ref":125},"121":{"$ref":126},"122":{"$ref":127},"123":{"$ref":128},"124":{"$ref":129},"125":{"$ref":130},"126":{"$ref":131},"127":{"$ref":132},"128":{"$ref":133},"129":{"$ref":134},"130":{"$ref":135},"131":{"$ref":136},"132":{"$ref":137},"133":{"$ref":138},"134":{"$ref":139},"135":{"$ref":140},"136":{"$ref":141},"137":{"$ref":142},"138":{"$ref":143},"139":{"$ref":144},"140":{"$ref":145},"141":{"$ref":146},"142":{"$ref":147},"143":{"$ref":148},"144":{"$ref":149},"145":{"$ref":150},"146":{"$ref":151},"147":{"$ref":152},"148":{"$ref":153},"149":{"$ref":154},"150":{"$ref":155},"151":{"$ref":156},"152":{"$ref":157},"153":{"$ref":158},"154":{"$ref":159},"155":{"$ref":160},"156":{"$ref":161},"157":{"$ref":162},"158":{"$ref":163},"159":{"$ref":164},"160":{"$ref":165},"161":{"$ref":166},"162":{"$ref":167},"163":{"$ref":168},"164":{"$ref":169},"165":{"$ref":170},"166":{"$ref":171},"167":{"$ref":172},"168":{"$ref":173},"169":{"$ref":174},"170":{"$ref":175},"171":{"$ref":176},"172":{"$ref":177},"173":{"$ref":178},"174":{"$ref":179},"175":{"$ref":180},"176":{"$ref":181},"177":{"$ref":182},"178":{"$ref":183},"179":{"$ref":184},"180":{"$ref":185},"181":{"$ref":186},"182":{"$ref":187},"183":{"$ref":188},"184":{"$ref":189},"185":{"$ref":190},"186":{"$ref":191},"187":{"$ref":192},"188":{"$ref":193},"189":{"$ref":194},"190":{"$ref":195},"191":{"$ref":196},"192":{"$ref":197},"193":{"$ref":198},"194":{"$ref":199},"195":{"$ref":200},"196":{"$ref":201},"197":{"$ref":202},"198":{"$ref":203},"199":{"$ref":204},"200":{"$ref":205},"201":{"$ref":206},"202":{"$ref":207},"203":{"$ref":208},"204":{"$ref":209},"205":{"$ref":210},"206":{"$ref":211},"207":{"$ref":212},"208":{"$ref":213},"209":{"$ref":214},"210":{"$ref":215},"211":{"$ref":216},"212":{"$ref":217},"213":{"$ref":218},"214":{"$ref":219},"215":{"$ref":220},"216":{"$ref":221},"217":{"$ref":222},"218":{"$ref":223},"219":{"$ref":224},"220":{"$ref":225},"221":{"$ref":226},"222":{"$ref":227},"223":{"$ref":228},"224":{"$ref":229},"225":{"$ref":230},"226":{"$ref":231},"227":{"$ref":232},"228":{"$ref":233},"229":{"$ref":234},"230":{"$ref":235},"231":{"$ref":236},"232":{"$ref":237},"233":{"$ref":238},"234":{"$ref":239},"235":{"$ref":240},"236":{"$ref":241},"237":{"$ref":242},"238":{"$ref":243},"239":{"$ref":244},"240":{"$ref":245},"241":{"$ref":246},"0":{"$ref":247}},"4":{"1":"sethiddenproperty","2":"string","3":"Pants","4":"pcall","5":"RightGrip","6":"floor","7":"make_writable","8":"Accessory","9":"Weld","10":"Instance","11":"esp","12":"checkifgay","13":"antiaim","14":"ModuleScript","15":"modifyguns","16":"write_clipboard","17":"create_secure_function","18":"Mouse","19":"BodyForce","20":"Vector3","21":"ReplicatedStorage","22":"RenderSettings","23":"set_thread_identity","24":"number","25":"BreakJoints","26":"RemoteEvent","27":"getrenv","28":"FilteringEnabled","29":"tick","30":"god","31":"LocalScript","32":"FOV","33":"Shoot","34":"workspace","35":"bool","36":"random","37":"crashserver","38":"Seat","39":"BrianSucksVexu","40":"MouseButton1Click","41":"SoundService","42":"warn","43":"CFrame","44":"JobId","45":"GetDescendants","46":"Zombies","47":"getrawmetatable","48":"hookfunction","49":"CoreGui","50":"Color3","51":"NetworkMarker","52":2000,"53":"Frame","54":"Ragdoll","55":"getgc","56":"JointsService","57":"SayMessageRequest","58":"Parent","59":"new","60":"Geometry","61":"PointsService","62":"UDim","63":"BasePart","64":"TweenInfo","65":"Character","66":"TweenService","67":"secrun","68":"IntValue","69":"gethiddenproperty","70":"Health","71":"PlayerGui","72":"int","73":"getgenv","74":"Changed","75":"sub","76":"tostring","77":"UserInputService","78":"Tween","79":"Path","80":"insert","81":"settings","82":"Trail","83":"VirtualUser","84":"concat","85":"type","86":"SimulationRadiusLocaleId","87":"Gravity","88":"getreg","89":"IsA","90":"autoshoot","91":"is_cached","92":"usertype","93":"NumberRange","94":"table","95":"Player","96":"firesignal","97":"Enabled","98":"RemoteFunction","99":"GuiService","100":"Tool","101":"chatspam","102":"secure_call","103":"'","104":"VRService","105":"LocalPlayer","106":"\n","107":"get_thread_identity","108":"Shirt","109":"getteams","110":"queue_on_teleport","111":"Shell","112":"Value","113":"TextBox","114":"a34534345 = '","115":"TeleportService","116":"wait","117":"Humanoid","118":"Stepped","119":"request","120":"run_secure_function","121":"Handle","122":"Players","123":"spawn","124":"UDim2","125":"hi","126":"protect_gui","127":"BodyGyro","128":"require","129":"print","130":"crypt","131":"FindFirstChild","132":"aimbot","133":"is_beta","134":"WalkSpeed","135":"HumanoidRootPart","136":"service","137":"Enum","138":"Chat","139":"plr","140":"error","141":"getnearest","142":"RunService","143":"userdata","144":"FireServer","145":"LuaSettings","146":"ReplicatedFirst","147":"Camera","148":"GetService","149":"Asset","150":"KeyCode","151":"fire","152":"saveinstance","153":"Teleport","154":"godmode","155":"Lighting","156":"Chatted","157":"websocket","158":"function","159":"unprotect_gui","160":"DefaultChatSystemChatEvents","161":"true","162":"debug","163":"changeupvalues","164":"Ray","165":"crypto","166":"Vector2","167":"getconnections","168":"fireclickdetector","169":"setreadonly","170":"StringValue","171":"ScreenGui","172":"math","173":"Debris","174":"Activated","175":"false","176":"Teams","177":"checkifalive","178":"run_secure_lua","179":"GetChildren","180":"NumberSequence","181":"infammo","182":"syn","183":"TextService","184":"FileMesh","185":"CurrentCamera","186":1,"187":"cache_replace","188":"GameId","189":"GameSettings","190":"create","191":"Name","192":"_G","193":"SkateboardPlatform","194":"cache_invalidate","195":"decompile","196":"game","197":"Decal","198":"BindableEvent","199":"Backpack","200":"Terrain","201":"HopperBin","202":"LogService","203":"getcross","204":"InputObject","0":"InvokeServer"},"5":{"S1lm":{"$ref":248},"808614":2,"-63713":{"$ref":249},"f7VW":0,"yNAmpf":0,"S1U":{"$ref":250}},"6":{"245690.28573986297":4,"35451.04005413784":11,"vLGd4":0,"Xv8Zvzy9C":0,"999221.35777985316":{"$ref":7},"Xr09QRU":94},"7":{"245690.28573986297":4,"35451.04005413784":4,"vLGd4":84,"Xv8Zvzy9C":0,"999221.35777985316":{"$ref":8},"Xr09QRU":4},"8":{"245690.28573986297":5,"35451.04005413784":20,"vLGd4":0,"Xv8Zvzy9C":0,"999221.35777985316":{"$ref":9},"Xr09QRU":3},"9":{"245690.28573986297":6,"35451.04005413784":2,"vLGd4":0,"Xv8Zvzy9C":0,"999221.35777985316":{"$ref":10},"Xr09QRU":106},"10":{"245690.28573986297":4,"35451.04005413784":6,"vLGd4":0,"Xv8Zvzy9C":0,"999221.35777985316":{"$ref":11},"Xr09QRU":6},"11":{"245690.28573986297":4,"35451.04005413784":11,"vLGd4":0,"Xv8Zvzy9C":0,"999221.35777985316":{"$ref":12},"Xr09QRU":129},"12":{"245690.28573986297":5,"35451.04005413784":2,"vLGd4":0,"Xv8Zvzy9C":0,"999221.35777985316":{"$ref":13},"Xr09QRU":125},"13":{"245690.28573986297":4,"35451.04005413784":18,"vLGd4":0,"Xv8Zvzy9C":0,"999221.35777985316":{"$ref":14},"Xr09QRU":0},"14":{"245690.28573986297":0,"35451.04005413784":26,"vLGd4":0,"Xv8Zvzy9C":0,"999221.35777985316":{"$ref":15},"Xr09QRU":0},"15":{"245690.28573986297":8,"35451.04005413784":11,"vLGd4":0,"Xv8Zvzy9C":0,"999221.35777985316":{"$ref":16},"Xr09QRU":94},"16":{"245690.28573986297":8,"35451.04005413784":4,"vLGd4":80,"Xv8Zvzy9C":0,"999221.35777985316":{"$ref":17},"Xr09QRU":8},"17":{"245690.28573986297":9,"35451.04005413784":20,"vLGd4":0,"Xv8Zvzy9C":0,"999221.35777985316":{"$ref":18},"Xr09QRU":3},"18":{"245690.28573986297":10,"35451.04005413784":2,"vLGd4":0,"Xv8Zvzy9C":0,"999221.35777985316":{"$ref":19},"Xr09QRU":114},"19":{"245690.28573986297":11,"35451.04005413784":11,"vLGd4":0,"Xv8Zvzy9C":0,"999221.35777985316":{"$ref":20},"Xr09QRU":76},"20":{"245690.28573986297":12,"35451.04005413784":11,"vLGd4":0,"Xv8Zvzy9C":0,"999221.35777985316":{"$ref":21},"Xr09QRU":172},"21":{"245690.28573986297":12,"35451.04005413784":4,"vLGd4":36,"Xv8Zvzy9C":0,"999221.35777985316":{"$ref":22},"Xr09QRU":12},"22":{"245690.28573986297":13,"35451.04005413784":2,"vLGd4":0,"Xv8Zvzy9C":0,"999221.35777985316":{"$ref":23},"Xr09QRU":186},"23":{"245690.28573986297":14,"35451.04005413784":25,"vLGd4":0,"Xv8Zvzy9C":0,"999221.35777985316":{"$ref":24},"Xr09QRU":2},"24":{"245690.28573986297":12,"35451.04005413784":7,"vLGd4":0,"Xv8Zvzy9C":0,"999221.35777985316":{"$ref":25},"Xr09QRU":14},"25":{"245690.28573986297":12,"35451.04005413784":16,"vLGd4":12,"Xv8Zvzy9C":0,"999221.35777985316":{"$ref":26},"Xr09QRU":2},"26":{"245690.28573986297":11,"35451.04005413784":13,"vLGd4":0,"Xv8Zvzy9C":0,"999221.35777985316":{"$ref":27},"Xr09QRU":0},"27":{"245690.28573986297":12,"35451.04005413784":2,"vLGd4":0,"Xv8Zvzy9C":0,"999221.35777985316":{"$ref":28},"Xr09QRU":103},"28":{"245690.28573986297":10,"35451.04005413784":22,"vLGd4":12,"Xv8Zvzy9C":0,"999221.35777985316":{"$ref":29},"Xr09QRU":10},"29":{"245690.28573986297":8,"35451.04005413784":6,"vLGd4":0,"Xv8Zvzy9C":0,"999221.35777985316":{"$ref":30},"Xr09QRU":10},"30":{"245690.28573986297":0,"35451.04005413784":15,"vLGd4":0,"Xv8Zvzy9C":0,"999221.35777985316":{"$ref":31},"Xr09QRU":{"$ref":31}},"31":{"245690.28573986297":4,"35451.04005413784":19,"vLGd4":0,"Xv8Zvzy9C":0,"999221.35777985316":{"$ref":6},"Xr09QRU":{"$ref":15}},"32":{"245690.28573986297":0,"35451.04005413784":15,"vLGd4":0,"Xv8Zvzy9C":0,"999221.35777985316":{"$ref":33},"Xr09QRU":{"$ref":6}},"33":{"245690.28573986297":0,"35451.04005413784":24,"vLGd4":0,"Xv8Zvzy9C":0,"999221.35777985316":{"$ref":34},"Xr09QRU":0},"34":{"245690.28573986297":0,"35451.04005413784":1,"vLGd4":0,"Xv8Zvzy9C":0,"999221.35777985316":{"$ref":35},"Xr09QRU":0},"35":{"245690.28573986297":1,"35451.04005413784":2,"vLGd4":0,"Xv8Zvzy9C":0,"999221.35777985316":{"$ref":36},"Xr09QRU":52},"36":{"245690.28573986297":2,"35451.04005413784":3,"vLGd4":0,"Xv8Zvzy9C":0,"999221.35777985316":{"$ref":37},"Xr09QRU":45},"37":{"245690.28573986297":3,"35451.04005413784":2,"vLGd4":0,"Xv8Zvzy9C":0,"999221.35777985316":{"$ref":38},"Xr09QRU":160},"38":{"245690.28573986297":4,"35451.04005413784":2,"vLGd4":0,"Xv8Zvzy9C":0,"999221.35777985316":{"$ref":39},"Xr09QRU":67},"39":{"245690.28573986297":5,"35451.04005413784":2,"vLGd4":0,"Xv8Zvzy9C":0,"999221.35777985316":{"$ref":40},"Xr09QRU":133},"40":{"245690.28573986297":6,"35451.04005413784":2,"vLGd4":0,"Xv8Zvzy9C":0,"999221.35777985316":{"$ref":41},"Xr09QRU":102},"41":{"245690.28573986297":7,"35451.04005413784":2,"vLGd4":0,"Xv8Zvzy9C":0,"999221.35777985316":{"$ref":42},"Xr09QRU":187},"42":{"245690.28573986297":8,"35451.04005413784":2,"vLGd4":0,"Xv8Zvzy9C":0,"999221.35777985316":{"$ref":43},"Xr09QRU":107},"43":{"245690.28573986297":9,"35451.04005413784":2,"vLGd4":0,"Xv8Zvzy9C":0,"999221.35777985316":{"$ref":44},"Xr09QRU":119},"44":{"245690.28573986297":10,"35451.04005413784":2,"vLGd4":0,"Xv8Zvzy9C":0,"999221.35777985316":{"$ref":45},"Xr09QRU":126},"45":{"245690.28573986297":11,"35451.04005413784":2,"vLGd4":0,"Xv8Zvzy9C":0,"999221.35777985316":{"$ref":46},"Xr09QRU":178},"46":{"245690.28573986297":12,"35451.04005413784":2,"vLGd4":0,"Xv8Zvzy9C":0,"999221.35777985316":{"$ref":47},"Xr09QRU":194},"47":{"245690.28573986297":13,"35451.04005413784":2,"vLGd4":0,"Xv8Zvzy9C":0,"999221.35777985316":{"$ref":48},"Xr09QRU":110},"48":{"245690.28573986297":14,"35451.04005413784":2,"vLGd4":0,"Xv8Zvzy9C":0,"999221.35777985316":{"$ref":49},"Xr09QRU":91},"49":{"245690.28573986297":15,"35451.04005413784":2,"vLGd4":0,"Xv8Zvzy9C":0,"999221.35777985316":{"$ref":50},"Xr09QRU":23},"50":{"245690.28573986297":16,"35451.04005413784":2,"vLGd4":0,"Xv8Zvzy9C":0,"999221.35777985316":{"$ref":51},"Xr09QRU":16},"51":{"245690.28573986297":17,"35451.04005413784":2,"vLGd4":0,"Xv8Zvzy9C":0,"999221.35777985316":{"$ref":52},"Xr09QRU":120},"52":{"245690.28573986297":18,"35451.04005413784":2,"vLGd4":0,"Xv8Zvzy9C":0,"999221.35777985316":{"$ref":53},"Xr09QRU":165},"53":{"245690.28573986297":19,"35451.04005413784":2,"vLGd4":0,"Xv8Zvzy9C":0,"999221.35777985316":{"$ref":54},"Xr09QRU":157},"54":{"245690.28573986297":20,"35451.04005413784":2,"vLGd4":0,"Xv8Zvzy9C":0,"999221.35777985316":{"$ref":55},"Xr09QRU":159},"55":{"245690.28573986297":21,"35451.04005413784":2,"vLGd4":0,"Xv8Zvzy9C":0,"999221.35777985316":{"$ref":56},"Xr09QRU":17},"56":{"245690.28573986297":22,"35451.04005413784":2,"vLGd4":0,"Xv8Zvzy9C":0,"999221.35777985316":{"$ref":57},"Xr09QRU":130},"57":{"245690.28573986297":23,"35451.04005413784":2,"vLGd4":0,"Xv8Zvzy9C":0,"999221.35777985316":{"$ref":58},"Xr09QRU":182},"58":{"245690.28573986297":24,"35451.04005413784":2,"vLGd4":0,"Xv8Zvzy9C":0,"999221.35777985316":{"$ref":59},"Xr09QRU":119},"59":{"245690.28573986297":25,"35451.04005413784":2,"vLGd4":0,"Xv8Zvzy9C":0,"999221.35777985316":{"$ref":60},"Xr09QRU":57},"60":{"245690.28573986297":26,"35451.04005413784":2,"vLGd4":0,"Xv8Zvzy9C":0,"999221.35777985316":{"$ref":61},"Xr09QRU":144},"61":{"245690.28573986297":27,"35451.04005413784":2,"vLGd4":0,"Xv8Zvzy9C":0,"999221.35777985316":{"$ref":62},"Xr09QRU":0},"62":{"245690.28573986297":28,"35451.04005413784":2,"vLGd4":0,"Xv8Zvzy9C":0,"999221.35777985316":{"$ref":63},"Xr09QRU":29},"63":{"245690.28573986297":29,"35451.04005413784":2,"vLGd4":0,"Xv8Zvzy9C":0,"999221.35777985316":{"$ref":64},"Xr09QRU":4},"64":{"245690.28573986297":30,"35451.04005413784":2,"vLGd4":0,"Xv8Zvzy9C":0,"999221.35777985316":{"$ref":65},"Xr09QRU":123},"65":{"245690.28573986297":31,"35451.04005413784":2,"vLGd4":0,"Xv8Zvzy9C":0,"999221.35777985316":{"$ref":66},"Xr09QRU":129},"66":{"245690.28573986297":32,"35451.04005413784":2,"vLGd4":0,"Xv8Zvzy9C":0,"999221.35777985316":{"$ref":67},"Xr09QRU":42},"67":{"245690.28573986297":33,"35451.04005413784":2,"vLGd4":0,"Xv8Zvzy9C":0,"999221.35777985316":{"$ref":68},"Xr09QRU":196},"68":{"245690.28573986297":34,"35451.04005413784":2,"vLGd4":0,"Xv8Zvzy9C":0,"999221.35777985316":{"$ref":69},"Xr09QRU":148},"69":{"245690.28573986297":35,"35451.04005413784":2,"vLGd4":0,"Xv8Zvzy9C":0,"999221.35777985316":{"$ref":70},"Xr09QRU":55},"70":{"245690.28573986297":36,"35451.04005413784":2,"vLGd4":0,"Xv8Zvzy9C":0,"999221.35777985316":{"$ref":71},"Xr09QRU":88},"71":{"245690.28573986297":37,"35451.04005413784":2,"vLGd4":0,"Xv8Zvzy9C":0,"999221.35777985316":{"$ref":72},"Xr09QRU":27},"72":{"245690.28573986297":38,"35451.04005413784":2,"vLGd4":0,"Xv8Zvzy9C":0,"999221.35777985316":{"$ref":73},"Xr09QRU":73},"73":{"245690.28573986297":39,"35451.04005413784":2,"vLGd4":0,"Xv8Zvzy9C":0,"999221.35777985316":{"$ref":74},"Xr09QRU":162},"74":{"245690.28573986297":40,"35451.04005413784":2,"vLGd4":0,"Xv8Zvzy9C":0,"999221.35777985316":{"$ref":75},"Xr09QRU":128},"75":{"245690.28573986297":41,"35451.04005413784":2,"vLGd4":0,"Xv8Zvzy9C":0,"999221.35777985316":{"$ref":76},"Xr09QRU":14},"76":{"245690.28573986297":42,"35451.04005413784":2,"vLGd4":0,"Xv8Zvzy9C":0,"999221.35777985316":{"$ref":77},"Xr09QRU":31},"77":{"245690.28573986297":43,"35451.04005413784":2,"vLGd4":0,"Xv8Zvzy9C":0,"999221.35777985316":{"$ref":78},"Xr09QRU":179},"78":{"245690.28573986297":44,"35451.04005413784":2,"vLGd4":0,"Xv8Zvzy9C":0,"999221.35777985316":{"$ref":79},"Xr09QRU":45},"79":{"245690.28573986297":45,"35451.04005413784":2,"vLGd4":0,"Xv8Zvzy9C":0,"999221.35777985316":{"$ref":80},"Xr09QRU":158},"80":{"245690.28573986297":46,"35451.04005413784":2,"vLGd4":0,"Xv8Zvzy9C":0,"999221.35777985316":{"$ref":81},"Xr09QRU":81},"81":{"245690.28573986297":47,"35451.04005413784":2,"vLGd4":0,"Xv8Zvzy9C":0,"999221.35777985316":{"$ref":82},"Xr09QRU":189},"82":{"245690.28573986297":48,"35451.04005413784":2,"vLGd4":0,"Xv8Zvzy9C":0,"999221.35777985316":{"$ref":83},"Xr09QRU":22},"83":{"245690.28573986297":49,"35451.04005413784":2,"vLGd4":0,"Xv8Zvzy9C":0,"999221.35777985316":{"$ref":84},"Xr09QRU":2},"84":{"245690.28573986297":50,"35451.04005413784":2,"vLGd4":0,"Xv8Zvzy9C":0,"999221.35777985316":{"$ref":85},"Xr09QRU":75},"85":{"245690.28573986297":51,"35451.04005413784":2,"vLGd4":0,"Xv8Zvzy9C":0,"999221.35777985316":{"$ref":86},"Xr09QRU":136},"86":{"245690.28573986297":52,"35451.04005413784":2,"vLGd4":0,"Xv8Zvzy9C":0,"999221.35777985316":{"$ref":87},"Xr09QRU":89},"87":{"245690.28573986297":2,"35451.04005413784":9,"vLGd4":1,"Xv8Zvzy9C":0,"999221.35777985316":{"$ref":88},"Xr09QRU":52},"88":{"245690.28573986297":3,"35451.04005413784":2,"vLGd4":0,"Xv8Zvzy9C":0,"999221.35777985316":{"$ref":89},"Xr09QRU":58},"89":{"245690.28573986297":4,"35451.04005413784":2,"vLGd4":0,"Xv8Zvzy9C":0,"999221.35777985316":{"$ref":90},"Xr09QRU":191},"90":{"245690.28573986297":5,"35451.04005413784":2,"vLGd4":0,"Xv8Zvzy9C":0,"999221.35777985316":{"$ref":91},"Xr09QRU":142},"91":{"245690.28573986297":6,"35451.04005413784":2,"vLGd4":0,"Xv8Zvzy9C":0,"999221.35777985316":{"$ref":92},"Xr09QRU":118},"92":{"245690.28573986297":7,"35451.04005413784":2,"vLGd4":0,"Xv8Zvzy9C":0,"999221.35777985316":{"$ref":93},"Xr09QRU":116},"93":{"245690.28573986297":8,"35451.04005413784":2,"vLGd4":0,"Xv8Zvzy9C":0,"999221.35777985316":{"$ref":94},"Xr09QRU":74},"94":{"245690.28573986297":9,"35451.04005413784":2,"vLGd4":0,"Xv8Zvzy9C":0,"999221.35777985316":{"$ref":95},"Xr09QRU":131},"95":{"245690.28573986297":10,"35451.04005413784":2,"vLGd4":0,"Xv8Zvzy9C":0,"999221.35777985316":{"$ref":96},"Xr09QRU":200},"96":{"245690.28573986297":11,"35451.04005413784":2,"vLGd4":0,"Xv8Zvzy9C":0,"999221.35777985316":{"$ref":97},"Xr09QRU":155},"97":{"245690.28573986297":12,"35451.04005413784":2,"vLGd4":0,"Xv8Zvzy9C":0,"999221.35777985316":{"$ref":98},"Xr09QRU":97},"98":{"245690.28573986297":13,"35451.04005413784":2,"vLGd4":0,"Xv8Zvzy9C":0,"999221.35777985316":{"$ref":99},"Xr09QRU":167},"99":{"245690.28573986297":14,"35451.04005413784":2,"vLGd4":0,"Xv8Zvzy9C":0,"999221.35777985316":{"$ref":100},"Xr09QRU":96},"100":{"245690.28573986297":15,"35451.04005413784":2,"vLGd4":0,"Xv8Zvzy9C":0,"999221.35777985316":{"$ref":101},"Xr09QRU":34},"101":{"245690.28573986297":16,"35451.04005413784":2,"vLGd4":0,"Xv8Zvzy9C":0,"999221.35777985316":{"$ref":102},"Xr09QRU":161},"102":{"245690.28573986297":17,"35451.04005413784":2,"vLGd4":0,"Xv8Zvzy9C":0,"999221.35777985316":{"$ref":103},"Xr09QRU":175},"103":{"245690.28573986297":18,"35451.04005413784":2,"vLGd4":0,"Xv8Zvzy9C":0,"999221.35777985316":{"$ref":104},"Xr09QRU":76},"104":{"245690.28573986297":19,"35451.04005413784":2,"vLGd4":0,"Xv8Zvzy9C":0,"999221.35777985316":{"$ref":105},"Xr09QRU":94},"105":{"245690.28573986297":20,"35451.04005413784":2,"vLGd4":0,"Xv8Zvzy9C":0,"999221.35777985316":{"$ref":106},"Xr09QRU":172},"106":{"245690.28573986297":21,"35451.04005413784":2,"vLGd4":0,"Xv8Zvzy9C":0,"999221.35777985316":{"$ref":107},"Xr09QRU":36},"107":{"245690.28573986297":22,"35451.04005413784":2,"vLGd4":0,"Xv8Zvzy9C":0,"999221.35777985316":{"$ref":108},"Xr09QRU":6},"108":{"245690.28573986297":23,"35451.04005413784":2,"vLGd4":0,"Xv8Zvzy9C":0,"999221.35777985316":{"$ref":109},"Xr09QRU":117},"109":{"245690.28573986297":24,"35451.04005413784":2,"vLGd4":0,"Xv8Zvzy9C":0,"999221.35777985316":{"$ref":110},"Xr09QRU":65},"110":{"245690.28573986297":25,"35451.04005413784":2,"vLGd4":0,"Xv8Zvzy9C":0,"999221.35777985316":{"$ref":111},"Xr09QRU":105},"111":{"245690.28573986297":26,"35451.04005413784":2,"vLGd4":0,"Xv8Zvzy9C":0,"999221.35777985316":{"$ref":112},"Xr09QRU":139},"112":{"245690.28573986297":27,"35451.04005413784":2,"vLGd4":0,"Xv8Zvzy9C":0,"999221.35777985316":{"$ref":113},"Xr09QRU":122},"113":{"245690.28573986297":28,"35451.04005413784":2,"vLGd4":0,"Xv8Zvzy9C":0,"999221.35777985316":{"$ref":114},"Xr09QRU":95},"114":{"245690.28573986297":29,"35451.04005413784":2,"vLGd4":0,"Xv8Zvzy9C":0,"999221.35777985316":{"$ref":115},"Xr09QRU":134},"115":{"245690.28573986297":30,"35451.04005413784":2,"vLGd4":0,"Xv8Zvzy9C":0,"999221.35777985316":{"$ref":116},"Xr09QRU":137},"116":{"245690.28573986297":31,"35451.04005413784":2,"vLGd4":0,"Xv8Zvzy9C":0,"999221.35777985316":{"$ref":117},"Xr09QRU":150},"117":{"245690.28573986297":32,"35451.04005413784":2,"vLGd4":0,"Xv8Zvzy9C":0,"999221.35777985316":{"$ref":118},"Xr09QRU":192},"118":{"245690.28573986297":33,"35451.04005413784":2,"vLGd4":0,"Xv8Zvzy9C":0,"999221.35777985316":{"$ref":119},"Xr09QRU":25},"119":{"245690.28573986297":34,"35451.04005413784":2,"vLGd4":0,"Xv8Zvzy9C":0,"999221.35777985316":{"$ref":120},"Xr09QRU":70},"120":{"245690.28573986297":35,"35451.04005413784":2,"vLGd4":0,"Xv8Zvzy9C":0,"999221.35777985316":{"$ref":121},"Xr09QRU":156},"121":{"245690.28573986297":36,"35451.04005413784":2,"vLGd4":0,"Xv8Zvzy9C":0,"999221.35777985316":{"$ref":122},"Xr09QRU":26},"122":{"245690.28573986297":37,"35451.04005413784":2,"vLGd4":0,"Xv8Zvzy9C":0,"999221.35777985316":{"$ref":123},"Xr09QRU":98},"123":{"245690.28573986297":38,"35451.04005413784":2,"vLGd4":0,"Xv8Zvzy9C":0,"999221.35777985316":{"$ref":124},"Xr09QRU":47},"124":{"245690.28573986297":39,"35451.04005413784":2,"vLGd4":0,"Xv8Zvzy9C":0,"999221.35777985316":{"$ref":125},"Xr09QRU":7},"125":{"245690.28573986297":40,"35451.04005413784":2,"vLGd4":0,"Xv8Zvzy9C":0,"999221.35777985316":{"$ref":126},"Xr09QRU":169},"126":{"245690.28573986297":41,"35451.04005413784":2,"vLGd4":0,"Xv8Zvzy9C":0,"999221.35777985316":{"$ref":127},"Xr09QRU":61},"127":{"245690.28573986297":42,"35451.04005413784":2,"vLGd4":0,"Xv8Zvzy9C":0,"999221.35777985316":{"$ref":128},"Xr09QRU":56},"128":{"245690.28573986297":43,"35451.04005413784":2,"vLGd4":0,"Xv8Zvzy9C":0,"999221.35777985316":{"$ref":129},"Xr09QRU":104},"129":{"245690.28573986297":44,"35451.04005413784":2,"vLGd4":0,"Xv8Zvzy9C":0,"999221.35777985316":{"$ref":130},"Xr09QRU":54},"130":{"245690.28573986297":45,"35451.04005413784":2,"vLGd4":0,"Xv8Zvzy9C":0,"999221.35777985316":{"$ref":131},"Xr09QRU":86},"131":{"245690.28573986297":46,"35451.04005413784":2,"vLGd4":0,"Xv8Zvzy9C":0,"999221.35777985316":{"$ref":132},"Xr09QRU":69},"132":{"245690.28573986297":47,"35451.04005413784":2,"vLGd4":0,"Xv8Zvzy9C":0,"999221.35777985316":{"$ref":133},"Xr09QRU":1},"133":{"245690.28573986297":48,"35451.04005413784":2,"vLGd4":0,"Xv8Zvzy9C":0,"999221.35777985316":{"$ref":134},"Xr09QRU":182},"134":{"245690.28573986297":49,"35451.04005413784":2,"vLGd4":0,"Xv8Zvzy9C":0,"999221.35777985316":{"$ref":135},"Xr09QRU":46},"135":{"245690.28573986297":50,"35451.04005413784":2,"vLGd4":0,"Xv8Zvzy9C":0,"999221.35777985316":{"$ref":136},"Xr09QRU":188},"136":{"245690.28573986297":51,"35451.04005413784":2,"vLGd4":0,"Xv8Zvzy9C":0,"999221.35777985316":{"$ref":137},"Xr09QRU":44},"137":{"245690.28573986297":52,"35451.04005413784":2,"vLGd4":0,"Xv8Zvzy9C":0,"999221.35777985316":{"$ref":138},"Xr09QRU":100},"138":{"245690.28573986297":2,"35451.04005413784":9,"vLGd4":2,"Xv8Zvzy9C":0,"999221.35777985316":{"$ref":139},"Xr09QRU":52},"139":{"245690.28573986297":3,"35451.04005413784":2,"vLGd4":0,"Xv8Zvzy9C":0,"999221.35777985316":{"$ref":140},"Xr09QRU":8},"140":{"245690.28573986297":4,"35451.04005413784":2,"vLGd4":0,"Xv8Zvzy9C":0,"999221.35777985316":{"$ref":141},"Xr09QRU":5},"141":{"245690.28573986297":5,"35451.04005413784":2,"vLGd4":0,"Xv8Zvzy9C":0,"999221.35777985316":{"$ref":142},"Xr09QRU":9},"142":{"245690.28573986297":6,"35451.04005413784":2,"vLGd4":0,"Xv8Zvzy9C":0,"999221.35777985316":{"$ref":143},"Xr09QRU":135},"143":{"245690.28573986297":7,"35451.04005413784":2,"vLGd4":0,"Xv8Zvzy9C":0,"999221.35777985316":{"$ref":144},"Xr09QRU":99},"144":{"245690.28573986297":8,"35451.04005413784":2,"vLGd4":0,"Xv8Zvzy9C":0,"999221.35777985316":{"$ref":145},"Xr09QRU":49},"145":{"245690.28573986297":9,"35451.04005413784":2,"vLGd4":0,"Xv8Zvzy9C":0,"999221.35777985316":{"$ref":146},"Xr09QRU":198},"146":{"245690.28573986297":10,"35451.04005413784":2,"vLGd4":0,"Xv8Zvzy9C":0,"999221.35777985316":{"$ref":147},"Xr09QRU":151},"147":{"245690.28573986297":11,"35451.04005413784":2,"vLGd4":0,"Xv8Zvzy9C":0,"999221.35777985316":{"$ref":148},"Xr09QRU":19},"148":{"245690.28573986297":12,"35451.04005413784":2,"vLGd4":0,"Xv8Zvzy9C":0,"999221.35777985316":{"$ref":149},"Xr09QRU":138},"149":{"245690.28573986297":13,"35451.04005413784":2,"vLGd4":0,"Xv8Zvzy9C":0,"999221.35777985316":{"$ref":150},"Xr09QRU":71},"150":{"245690.28573986297":14,"35451.04005413784":2,"vLGd4":0,"Xv8Zvzy9C":0,"999221.35777985316":{"$ref":151},"Xr09QRU":51},"151":{"245690.28573986297":15,"35451.04005413784":2,"vLGd4":0,"Xv8Zvzy9C":0,"999221.35777985316":{"$ref":152},"Xr09QRU":60},"152":{"245690.28573986297":16,"35451.04005413784":2,"vLGd4":0,"Xv8Zvzy9C":0,"999221.35777985316":{"$ref":153},"Xr09QRU":183},"153":{"245690.28573986297":17,"35451.04005413784":2,"vLGd4":0,"Xv8Zvzy9C":0,"999221.35777985316":{"$ref":154},"Xr09QRU":202},"154":{"245690.28573986297":18,"35451.04005413784":2,"vLGd4":0,"Xv8Zvzy9C":0,"999221.35777985316":{"$ref":155},"Xr09QRU":140},"155":{"245690.28573986297":19,"35451.04005413784":2,"vLGd4":0,"Xv8Zvzy9C":0,"999221.35777985316":{"$ref":156},"Xr09QRU":145},"156":{"245690.28573986297":20,"35451.04005413784":2,"vLGd4":0,"Xv8Zvzy9C":0,"999221.35777985316":{"$ref":157},"Xr09QRU":77},"157":{"245690.28573986297":21,"35451.04005413784":2,"vLGd4":0,"Xv8Zvzy9C":0,"999221.35777985316":{"$ref":158},"Xr09QRU":168},"158":{"245690.28573986297":22,"35451.04005413784":2,"vLGd4":0,"Xv8Zvzy9C":0,"999221.35777985316":{"$ref":159},"Xr09QRU":82},"159":{"245690.28573986297":23,"35451.04005413784":2,"vLGd4":0,"Xv8Zvzy9C":0,"999221.35777985316":{"$ref":160},"Xr09QRU":147},"160":{"245690.28573986297":24,"35451.04005413784":2,"vLGd4":0,"Xv8Zvzy9C":0,"999221.35777985316":{"$ref":161},"Xr09QRU":185},"161":{"245690.28573986297":25,"35451.04005413784":2,"vLGd4":0,"Xv8Zvzy9C":0,"999221.35777985316":{"$ref":162},"Xr09QRU":32},"162":{"245690.28573986297":26,"35451.04005413784":2,"vLGd4":0,"Xv8Zvzy9C":0,"999221.35777985316":{"$ref":163},"Xr09QRU":79},"163":{"245690.28573986297":27,"35451.04005413784":2,"vLGd4":0,"Xv8Zvzy9C":0,"999221.35777985316":{"$ref":164},"Xr09QRU":204},"164":{"245690.28573986297":28,"35451.04005413784":2,"vLGd4":0,"Xv8Zvzy9C":0,"999221.35777985316":{"$ref":165},"Xr09QRU":53},"165":{"245690.28573986297":29,"35451.04005413784":2,"vLGd4":0,"Xv8Zvzy9C":0,"999221.35777985316":{"$ref":166},"Xr09QRU":113},"166":{"245690.28573986297":30,"35451.04005413784":2,"vLGd4":0,"Xv8Zvzy9C":0,"999221.35777985316":{"$ref":167},"Xr09QRU":171},"167":{"245690.28573986297":31,"35451.04005413784":2,"vLGd4":0,"Xv8Zvzy9C":0,"999221.35777985316":{"$ref":168},"Xr09QRU":48},"168":{"245690.28573986297":32,"35451.04005413784":2,"vLGd4":0,"Xv8Zvzy9C":0,"999221.35777985316":{"$ref":169},"Xr09QRU":173},"169":{"245690.28573986297":33,"35451.04005413784":2,"vLGd4":0,"Xv8Zvzy9C":0,"999221.35777985316":{"$ref":170},"Xr09QRU":21},"170":{"245690.28573986297":34,"35451.04005413784":2,"vLGd4":0,"Xv8Zvzy9C":0,"999221.35777985316":{"$ref":171},"Xr09QRU":146},"171":{"245690.28573986297":35,"35451.04005413784":2,"vLGd4":0,"Xv8Zvzy9C":0,"999221.35777985316":{"$ref":172},"Xr09QRU":195},"172":{"245690.28573986297":36,"35451.04005413784":2,"vLGd4":0,"Xv8Zvzy9C":0,"999221.35777985316":{"$ref":173},"Xr09QRU":152},"173":{"245690.28573986297":37,"35451.04005413784":2,"vLGd4":0,"Xv8Zvzy9C":0,"999221.35777985316":{"$ref":174},"Xr09QRU":66},"174":{"245690.28573986297":38,"35451.04005413784":2,"vLGd4":0,"Xv8Zvzy9C":0,"999221.35777985316":{"$ref":175},"Xr09QRU":41},"175":{"245690.28573986297":39,"35451.04005413784":2,"vLGd4":0,"Xv8Zvzy9C":0,"999221.35777985316":{"$ref":176},"Xr09QRU":176},"176":{"245690.28573986297":40,"35451.04005413784":2,"vLGd4":0,"Xv8Zvzy9C":0,"999221.35777985316":{"$ref":177},"Xr09QRU":78},"177":{"245690.28573986297":41,"35451.04005413784":2,"vLGd4":0,"Xv8Zvzy9C":0,"999221.35777985316":{"$ref":178},"Xr09QRU":63},"178":{"245690.28573986297":42,"35451.04005413784":2,"vLGd4":0,"Xv8Zvzy9C":0,"999221.35777985316":{"$ref":179},"Xr09QRU":38},"179":{"245690.28573986297":43,"35451.04005413784":2,"vLGd4":0,"Xv8Zvzy9C":0,"999221.35777985316":{"$ref":180},"Xr09QRU":197},"180":{"245690.28573986297":44,"35451.04005413784":2,"vLGd4":0,"Xv8Zvzy9C":0,"999221.35777985316":{"$ref":181},"Xr09QRU":10},"181":{"245690.28573986297":45,"35451.04005413784":2,"vLGd4":0,"Xv8Zvzy9C":0,"999221.35777985316":{"$ref":182},"Xr09QRU":59},"182":{"245690.28573986297":46,"35451.04005413784":2,"vLGd4":0,"Xv8Zvzy9C":0,"999221.35777985316":{"$ref":183},"Xr09QRU":164},"183":{"245690.28573986297":47,"35451.04005413784":2,"vLGd4":0,"Xv8Zvzy9C":0,"999221.35777985316":{"$ref":184},"Xr09QRU":64},"184":{"245690.28573986297":48,"35451.04005413784":2,"vLGd4":0,"Xv8Zvzy9C":0,"999221.35777985316":{"$ref":185},"Xr09QRU":50},"185":{"245690.28573986297":49,"35451.04005413784":2,"vLGd4":0,"Xv8Zvzy9C":0,"999221.35777985316":{"$ref":186},"Xr09QRU":43},"186":{"245690.28573986297":50,"35451.04005413784":2,"vLGd4":0,"Xv8Zvzy9C":0,"999221.35777985316":{"$ref":187},"Xr09QRU":20},"187":{"245690.28573986297":51,"35451.04005413784":2,"vLGd4":0,"Xv8Zvzy9C":0,"999221.35777985316":{"$ref":188},"Xr09QRU":166},"188":{"245690.28573986297":52,"35451.04005413784":2,"vLGd4":0,"Xv8Zvzy9C":0,"999221.35777985316":{"$ref":189},"Xr09QRU":62},"189":{"245690.28573986297":2,"35451.04005413784":9,"vLGd4":3,"Xv8Zvzy9C":0,"999221.35777985316":{"$ref":190},"Xr09QRU":52},"190":{"245690.28573986297":3,"35451.04005413784":2,"vLGd4":0,"Xv8Zvzy9C":0,"999221.35777985316":{"$ref":191},"Xr09QRU":124},"191":{"245690.28573986297":4,"35451.04005413784":2,"vLGd4":0,"Xv8Zvzy9C":0,"999221.35777985316":{"$ref":192},"Xr09QRU":93},"192":{"245690.28573986297":5,"35451.04005413784":2,"vLGd4":0,"Xv8Zvzy9C":0,"999221.35777985316":{"$ref":193},"Xr09QRU":180},"193":{"245690.28573986297":6,"35451.04005413784":2,"vLGd4":0,"Xv8Zvzy9C":0,"999221.35777985316":{"$ref":194},"Xr09QRU":121},"194":{"245690.28573986297":7,"35451.04005413784":2,"vLGd4":0,"Xv8Zvzy9C":0,"999221.35777985316":{"$ref":195},"Xr09QRU":87},"195":{"245690.28573986297":8,"35451.04005413784":2,"vLGd4":0,"Xv8Zvzy9C":0,"999221.35777985316":{"$ref":196},"Xr09QRU":201},"196":{"245690.28573986297":9,"35451.04005413784":2,"vLGd4":0,"Xv8Zvzy9C":0,"999221.35777985316":{"$ref":197},"Xr09QRU":108},"197":{"245690.28573986297":10,"35451.04005413784":2,"vLGd4":0,"Xv8Zvzy9C":0,"999221.35777985316":{"$ref":198},"Xr09QRU":3},"198":{"245690.28573986297":11,"35451.04005413784":2,"vLGd4":0,"Xv8Zvzy9C":0,"999221.35777985316":{"$ref":199},"Xr09QRU":18},"199":{"245690.28573986297":12,"35451.04005413784":2,"vLGd4":0,"Xv8Zvzy9C":0,"999221.35777985316":{"$ref":200},"Xr09QRU":68},"200":{"245690.28573986297":13,"35451.04005413784":2,"vLGd4":0,"Xv8Zvzy9C":0,"999221.35777985316":{"$ref":201},"Xr09QRU":170},"201":{"245690.28573986297":14,"35451.04005413784":2,"vLGd4":0,"Xv8Zvzy9C":0,"999221.35777985316":{"$ref":202},"Xr09QRU":112},"202":{"245690.28573986297":15,"35451.04005413784":2,"vLGd4":0,"Xv8Zvzy9C":0,"999221.35777985316":{"$ref":203},"Xr09QRU":83},"203":{"245690.28573986297":16,"35451.04005413784":2,"vLGd4":0,"Xv8Zvzy9C":0,"999221.35777985316":{"$ref":204},"Xr09QRU":40},"204":{"245690.28573986297":17,"35451.04005413784":2,"vLGd4":0,"Xv8Zvzy9C":0,"999221.35777985316":{"$ref":205},"Xr09QRU":174},"205":{"245690.28573986297":18,"35451.04005413784":2,"vLGd4":0,"Xv8Zvzy9C":0,"999221.35777985316":{"$ref":206},"Xr09QRU":184},"206":{"245690.28573986297":19,"35451.04005413784":2,"vLGd4":0,"Xv8Zvzy9C":0,"999221.35777985316":{"$ref":207},"Xr09QRU":115},"207":{"245690.28573986297":20,"35451.04005413784":2,"vLGd4":0,"Xv8Zvzy9C":0,"999221.35777985316":{"$ref":208},"Xr09QRU":153},"208":{"245690.28573986297":21,"35451.04005413784":2,"vLGd4":0,"Xv8Zvzy9C":0,"999221.35777985316":{"$ref":209},"Xr09QRU":143},"209":{"245690.28573986297":22,"35451.04005413784":2,"vLGd4":0,"Xv8Zvzy9C":0,"999221.35777985316":{"$ref":210},"Xr09QRU":2},"210":{"245690.28573986297":23,"35451.04005413784":2,"vLGd4":0,"Xv8Zvzy9C":0,"999221.35777985316":{"$ref":211},"Xr09QRU":72},"211":{"245690.28573986297":24,"35451.04005413784":2,"vLGd4":0,"Xv8Zvzy9C":0,"999221.35777985316":{"$ref":212},"Xr09QRU":24},"212":{"245690.28573986297":25,"35451.04005413784":2,"vLGd4":0,"Xv8Zvzy9C":0,"999221.35777985316":{"$ref":213},"Xr09QRU":35},"213":{"245690.28573986297":26,"35451.04005413784":2,"vLGd4":0,"Xv8Zvzy9C":0,"999221.35777985316":{"$ref":214},"Xr09QRU":127},"214":{"245690.28573986297":27,"35451.04005413784":2,"vLGd4":0,"Xv8Zvzy9C":0,"999221.35777985316":{"$ref":215},"Xr09QRU":199},"215":{"245690.28573986297":28,"35451.04005413784":2,"vLGd4":0,"Xv8Zvzy9C":0,"999221.35777985316":{"$ref":216},"Xr09QRU":193},"216":{"245690.28573986297":29,"35451.04005413784":2,"vLGd4":0,"Xv8Zvzy9C":0,"999221.35777985316":{"$ref":217},"Xr09QRU":28},"217":{"245690.28573986297":30,"35451.04005413784":2,"vLGd4":0,"Xv8Zvzy9C":0,"999221.35777985316":{"$ref":218},"Xr09QRU":33},"218":{"245690.28573986297":31,"35451.04005413784":2,"vLGd4":0,"Xv8Zvzy9C":0,"999221.35777985316":{"$ref":219},"Xr09QRU":111},"219":{"245690.28573986297":32,"35451.04005413784":2,"vLGd4":0,"Xv8Zvzy9C":0,"999221.35777985316":{"$ref":220},"Xr09QRU":149},"220":{"245690.28573986297":33,"35451.04005413784":2,"vLGd4":0,"Xv8Zvzy9C":0,"999221.35777985316":{"$ref":221},"Xr09QRU":12},"221":{"245690.28573986297":34,"35451.04005413784":2,"vLGd4":0,"Xv8Zvzy9C":0,"999221.35777985316":{"$ref":222},"Xr09QRU":190},"222":{"245690.28573986297":35,"35451.04005413784":2,"vLGd4":0,"Xv8Zvzy9C":0,"999221.35777985316":{"$ref":223},"Xr09QRU":30},"223":{"245690.28573986297":36,"35451.04005413784":2,"vLGd4":0,"Xv8Zvzy9C":0,"999221.35777985316":{"$ref":224},"Xr09QRU":39},"224":{"245690.28573986297":37,"35451.04005413784":2,"vLGd4":0,"Xv8Zvzy9C":0,"999221.35777985316":{"$ref":225},"Xr09QRU":177},"225":{"245690.28573986297":38,"35451.04005413784":2,"vLGd4":0,"Xv8Zvzy9C":0,"999221.35777985316":{"$ref":226},"Xr09QRU":109},"226":{"245690.28573986297":39,"35451.04005413784":2,"vLGd4":0,"Xv8Zvzy9C":0,"999221.35777985316":{"$ref":227},"Xr09QRU":141},"227":{"245690.28573986297":40,"35451.04005413784":2,"vLGd4":0,"Xv8Zvzy9C":0,"999221.35777985316":{"$ref":228},"Xr09QRU":203},"228":{"245690.28573986297":41,"35451.04005413784":2,"vLGd4":0,"Xv8Zvzy9C":0,"999221.35777985316":{"$ref":229},"Xr09QRU":90},"229":{"245690.28573986297":42,"35451.04005413784":2,"vLGd4":0,"Xv8Zvzy9C":0,"999221.35777985316":{"$ref":230},"Xr09QRU":101},"230":{"245690.28573986297":43,"35451.04005413784":2,"vLGd4":0,"Xv8Zvzy9C":0,"999221.35777985316":{"$ref":231},"Xr09QRU":163},"231":{"245690.28573986297":44,"35451.04005413784":2,"vLGd4":0,"Xv8Zvzy9C":0,"999221.35777985316":{"$ref":232},"Xr09QRU":15},"232":{"245690.28573986297":45,"35451.04005413784":2,"vLGd4":0,"Xv8Zvzy9C":0,"999221.35777985316":{"$ref":233},"Xr09QRU":181},"233":{"245690.28573986297":46,"35451.04005413784":2,"vLGd4":0,"Xv8Zvzy9C":0,"999221.35777985316":{"$ref":234},"Xr09QRU":154},"234":{"245690.28573986297":47,"35451.04005413784":2,"vLGd4":0,"Xv8Zvzy9C":0,"999221.35777985316":{"$ref":235},"Xr09QRU":132},"235":{"245690.28573986297":48,"35451.04005413784":2,"vLGd4":0,"Xv8Zvzy9C":0,"999221.35777985316":{"$ref":236},"Xr09QRU":11},"236":{"245690.28573986297":49,"35451.04005413784":2,"vLGd4":0,"Xv8Zvzy9C":0,"999221.35777985316":{"$ref":237},"Xr09QRU":37},"237":{"245690.28573986297":50,"35451.04005413784":2,"vLGd4":0,"Xv8Zvzy9C":0,"999221.35777985316":{"$ref":238},"Xr09QRU":13},"238":{"245690.28573986297":51,"35451.04005413784":2,"vLGd4":0,"Xv8Zvzy9C":0,"999221.35777985316":{"$ref":239},"Xr09QRU":92},"239":{"245690.28573986297":52,"35451.04005413784":2,"vLGd4":0,"Xv8Zvzy9C":0,"999221.35777985316":{"$ref":240},"Xr09QRU":85},"240":{"245690.28573986297":2,"35451.04005413784":9,"vLGd4":4,"Xv8Zvzy9C":0,"999221.35777985316":{"$ref":241},"Xr09QRU":52},"241":{"245690.28573986297":3,"35451.04005413784":21,"vLGd4":0,"Xv8Zvzy9C":0,"999221.35777985316":{"$ref":242},"Xr09QRU":0},"242":{"245690.28573986297":4,"35451.04005413784":2,"vLGd4":0,"Xv8Zvzy9C":0,"999221.35777985316":{"$ref":243},"Xr09QRU":186},"243":{"245690.28573986297":5,"35451.04005413784":20,"vLGd4":0,"Xv8Zvzy9C":0,"999221.35777985316":{"$ref":244},"Xr09QRU":1},"244":{"245690.28573986297":6,"35451.04005413784":2,"vLGd4":0,"Xv8Zvzy9C":0,"999221.35777985316":{"$ref":245},"Xr09QRU":186},"245":{"245690.28573986297":4,"35451.04005413784":5,"vLGd4":0,"Xv8Zvzy9C":0,"999221.35777985316":{"$ref":15},"Xr09QRU":{"$ref":31}},"246":{"245690.28573986297":0,"35451.04005413784":15,"vLGd4":0,"Xv8Zvzy9C":0,"Xr09QRU":{"$ref":15}},"247":{"245690.28573986297":0,"35451.04005413784":15,"vLGd4":0,"Xv8Zvzy9C":0,"999221.35777985316":{"$ref":6},"Xr09QRU":{"$ref":33}},"248":{},"249":{"1":{"$ref":251},"2":{"$ref":252},"3":{"$ref":253},"4":{"$ref":254},"0":{"$ref":255}},"250":{},"251":{"245690.28573986297":0,"35451.04005413784":26,"vLGd4":0,"Xv8Zvzy9C":0,"999221.35777985316":{"$ref":252},"Xr09QRU":0},"252":{"245690.28573986297":0,"35451.04005413784":24,"vLGd4":0,"Xv8Zvzy9C":0,"999221.35777985316":{"$ref":253},"Xr09QRU":0},"253":{"245690.28573986297":1,"35451.04005413784":23,"vLGd4":0,"Xv8Zvzy9C":0,"999221.35777985316":{"$ref":254},"Xr09QRU":0},"254":{"245690.28573986297":1,"35451.04005413784":10,"vLGd4":0,"Xv8Zvzy9C":0,"Xr09QRU":0},"255":{"245690.28573986297":0,"35451.04005413784":15,"vLGd4":0,"Xv8Zvzy9C":0,"999221.35777985316":{"$ref":251},"Xr09QRU":{"$ref":252}}}}